pyros2/__init__.py
pyros2/bridge.py
pyros2/client.py
pyros2/discovery.py
pyros2/exceptions.py
pyros2/launch.py
pyros2/launch_cli.py
pyros2/message.py
pyros2/message_translator.py
pyros2/node.py
pyros2/publisher.py
pyros2/qos.py
pyros2/service.py
pyros2/subscriber.py
pyros2/timer.py
python_ros_engine-1.0.1.dist-info/licenses/LICENSE
python_ros_engine-1.0.1.dist-info/METADATA
python_ros_engine-1.0.1.dist-info/WHEEL
python_ros_engine-1.0.1.dist-info/top_level.txt
python_ros_engine-1.0.1.dist-info/RECORD
